{
  "profCode": "PR009",
  "enrollments": [
    {
      "el": "EL116",
      "subject": "Cours d’arabe",
      "tab": "Rokya Sanogo",
      "sessions": [
        {
          "number": 1,
          "lessons": [
            {
              "number": 1,
              "date": "2026-04-11",
              "status": "PRESENT",
              "content": "Lecture et mémorisation de l'alphabet"
            },
            {
              "number": 2,
              "date": "2026-04-12",
              "status": "PRESENT",
              "content": "lecture des lettres avec les voyelles +les prolongations"
            },
            {
              "number": 3,
              "date": "2026-04-18",
              "status": "PRESENT",
              "content": "lecture des lettres avec tanween +les mots avec alif ba et ta"
            },
            {
              "number": 4,
              "date": "2026-04-19",
              "status": "PRESENT",
              "content": "suite de lecture des mots avec les illustrations"
            },
            {
              "number": 5,
              "date": "2026-04-25",
              "status": "PRESENT",
              "content": "Révision des mots et lecture des mots dans le tableau"
            },
            {
              "number": 6,
              "date": "2003-04-26",
              "status": "PRESENT",
              "content": "entraînement sur la lecture des mots dans le tableau et les mots avec illustration"
            },
            {
              "number": 7,
              "date": "2026-05-02",
              "status": "PRESENT",
              "content": "le cours de skoun avec des entraînements"
            },
            {
              "number": 8,
              "date": "2026-05-03",
              "status": "PRESENT",
              "content": "cours de chaddah avec des entraînements"
            }
          ]
        },
        {
          "number": 2,
          "lessons": [
            {
              "number": 1,
              "date": "2026-05-09",
              "status": "PRESENT",
              "content": null
            },
            {
              "number": 2,
              "date": "2026-05-10",
              "status": "PRESENT",
              "content": null
            },
            {
              "number": 3,
              "date": "2026-05-16",
              "status": "PRESENT",
              "content": null
            },
            {
              "number": 4,
              "date": "2026-05-17",
              "status": "PRESENT",
              "content": null
            },
            {
              "number": 5,
              "date": "2026-05-23",
              "status": "PRESENT",
              "content": null
            },
            {
              "number": 6,
              "date": "2026-05-24",
              "status": "PRESENT",
              "content": null
            },
            {
              "number": 7,
              "date": null,
              "status": "PENDING",
              "content": null
            },
            {
              "number": 8,
              "date": null,
              "status": "PENDING",
              "content": null
            }
          ]
        },
        {
          "number": 3,
          "lessons": [
            {
              "number": 1,
              "date": null,
              "status": "PENDING",
              "content": null
            },
            {
              "number": 2,
              "date": null,
              "status": "PENDING",
              "content": null
            },
            {
              "number": 3,
              "date": null,
              "status": "PENDING",
              "content": null
            },
            {
              "number": 4,
              "date": null,
              "status": "PENDING",
              "content": null
            },
            {
              "number": 5,
              "date": null,
              "status": "PENDING",
              "content": null
            },
            {
              "number": 6,
              "date": null,
              "status": "PENDING",
              "content": null
            },
            {
              "number": 7,
              "date": null,
              "status": "PENDING",
              "content": null
            },
            {
              "number": 8,
              "date": null,
              "status": "PENDING",
              "content": null
            }
          ]
        },
        {
          "number": 4,
          "lessons": [
            {
              "number": 1,
              "date": null,
              "status": "PENDING",
              "content": null
            },
            {
              "number": 2,
              "date": null,
              "status": "PENDING",
              "content": null
            },
            {
              "number": 3,
              "date": null,
              "status": "PENDING",
              "content": null
            },
            {
              "number": 4,
              "date": null,
              "status": "PENDING",
              "content": null
            },
            {
              "number": 5,
              "date": null,
              "status": "PENDING",
              "content": null
            },
            {
              "number": 6,
              "date": null,
              "status": "PENDING",
              "content": null
            },
            {
              "number": 7,
              "date": null,
              "status": "PENDING",
              "content": null
            },
            {
              "number": 8,
              "date": null,
              "status": "PENDING",
              "content": null
            }
          ]
        },
        {
          "number": 5,
          "lessons": [
            {
              "number": 1,
              "date": null,
              "status": "PENDING",
              "content": null
            },
            {
              "number": 2,
              "date": null,
              "status": "PENDING",
              "content": null
            },
            {
              "number": 3,
              "date": null,
              "status": "PENDING",
              "content": null
            },
            {
              "number": 4,
              "date": null,
              "status": "PENDING",
              "content": null
            },
            {
              "number": 5,
              "date": null,
              "status": "PENDING",
              "content": null
            },
            {
              "number": 6,
              "date": null,
              "status": "PENDING",
              "content": null
            },
            {
              "number": 7,
              "date": null,
              "status": "PENDING",
              "content": null
            },
            {
              "number": 8,
              "date": null,
              "status": "PENDING",
              "content": null
            }
          ]
        },
        {
          "number": 6,
          "lessons": [
            {
              "number": 1,
              "date": null,
              "status": "PENDING",
              "content": null
            },
            {
              "number": 2,
              "date": null,
              "status": "PENDING",
              "content": null
            },
            {
              "number": 3,
              "date": null,
              "status": "PENDING",
              "content": null
            },
            {
              "number": 4,
              "date": null,
              "status": "PENDING",
              "content": null
            },
            {
              "number": 5,
              "date": null,
              "status": "PENDING",
              "content": null
            },
            {
              "number": 6,
              "date": null,
              "status": "PENDING",
              "content": null
            },
            {
              "number": 7,
              "date": null,
              "status": "PENDING",
              "content": null
            },
            {
              "number": 8,
              "date": null,
              "status": "PENDING",
              "content": null
            }
          ]
        },
        {
          "number": 7,
          "lessons": [
            {
              "number": 1,
              "date": null,
              "status": "PENDING",
              "content": null
            },
            {
              "number": 2,
              "date": null,
              "status": "PENDING",
              "content": null
            },
            {
              "number": 3,
              "date": null,
              "status": "PENDING",
              "content": null
            },
            {
              "number": 4,
              "date": null,
              "status": "PENDING",
              "content": null
            },
            {
              "number": 5,
              "date": null,
              "status": "PENDING",
              "content": null
            },
            {
              "number": 6,
              "date": null,
              "status": "PENDING",
              "content": null
            },
            {
              "number": 7,
              "date": null,
              "status": "PENDING",
              "content": null
            },
            {
              "number": 8,
              "date": null,
              "status": "PENDING",
              "content": null
            }
          ]
        },
        {
          "number": 8,
          "lessons": [
            {
              "number": 1,
              "date": null,
              "status": "PENDING",
              "content": null
            },
            {
              "number": 2,
              "date": null,
              "status": "PENDING",
              "content": null
            },
            {
              "number": 3,
              "date": null,
              "status": "PENDING",
              "content": null
            },
            {
              "number": 4,
              "date": null,
              "status": "PENDING",
              "content": null
            },
            {
              "number": 5,
              "date": null,
              "status": "PENDING",
              "content": null
            },
            {
              "number": 6,
              "date": null,
              "status": "PENDING",
              "content": null
            },
            {
              "number": 7,
              "date": null,
              "status": "PENDING",
              "content": null
            },
            {
              "number": 8,
              "date": null,
              "status": "PENDING",
              "content": null
            }
          ]
        },
        {
          "number": 9,
          "lessons": [
            {
              "number": 1,
              "date": null,
              "status": "PENDING",
              "content": null
            },
            {
              "number": 2,
              "date": null,
              "status": "PENDING",
              "content": null
            },
            {
              "number": 3,
              "date": null,
              "status": "PENDING",
              "content": null
            },
            {
              "number": 4,
              "date": null,
              "status": "PENDING",
              "content": null
            },
            {
              "number": 5,
              "date": null,
              "status": "PENDING",
              "content": null
            },
            {
              "number": 6,
              "date": null,
              "status": "PENDING",
              "content": null
            },
            {
              "number": 7,
              "date": null,
              "status": "PENDING",
              "content": null
            },
            {
              "number": 8,
              "date": null,
              "status": "PENDING",
              "content": null
            }
          ]
        },
        {
          "number": 11,
          "lessons": [
            {
              "number": 1,
              "date": null,
              "status": "PENDING",
              "content": null
            },
            {
              "number": 2,
              "date": null,
              "status": "PENDING",
              "content": null
            },
            {
              "number": 3,
              "date": null,
              "status": "PENDING",
              "content": null
            },
            {
              "number": 4,
              "date": null,
              "status": "PENDING",
              "content": null
            },
            {
              "number": 5,
              "date": null,
              "status": "PENDING",
              "content": null
            },
            {
              "number": 6,
              "date": null,
              "status": "PENDING",
              "content": null
            },
            {
              "number": 7,
              "date": null,
              "status": "PENDING",
              "content": null
            },
            {
              "number": 8,
              "date": null,
              "status": "PENDING",
              "content": null
            }
          ]
        },
        {
          "number": 12,
          "lessons": [
            {
              "number": 1,
              "date": null,
              "status": "PENDING",
              "content": null
            },
            {
              "number": 2,
              "date": null,
              "status": "PENDING",
              "content": null
            },
            {
              "number": 3,
              "date": null,
              "status": "PENDING",
              "content": null
            },
            {
              "number": 4,
              "date": null,
              "status": "PENDING",
              "content": null
            },
            {
              "number": 5,
              "date": null,
              "status": "PENDING",
              "content": null
            },
            {
              "number": 6,
              "date": null,
              "status": "PENDING",
              "content": null
            },
            {
              "number": 7,
              "date": null,
              "status": "PENDING",
              "content": null
            },
            {
              "number": 8,
              "date": null,
              "status": "PENDING",
              "content": null
            }
          ]
        },
        {
          "number": 13,
          "lessons": [
            {
              "number": 1,
              "date": null,
              "status": "PENDING",
              "content": null
            },
            {
              "number": 2,
              "date": null,
              "status": "PENDING",
              "content": null
            },
            {
              "number": 3,
              "date": null,
              "status": "PENDING",
              "content": null
            },
            {
              "number": 4,
              "date": null,
              "status": "PENDING",
              "content": null
            },
            {
              "number": 5,
              "date": null,
              "status": "PENDING",
              "content": null
            },
            {
              "number": 6,
              "date": null,
              "status": "PENDING",
              "content": null
            },
            {
              "number": 7,
              "date": null,
              "status": "PENDING",
              "content": null
            },
            {
              "number": 8,
              "date": null,
              "status": "PENDING",
              "content": null
            }
          ]
        },
        {
          "number": 14,
          "lessons": [
            {
              "number": 1,
              "date": null,
              "status": "PENDING",
              "content": null
            },
            {
              "number": 2,
              "date": null,
              "status": "PENDING",
              "content": null
            },
            {
              "number": 3,
              "date": null,
              "status": "PENDING",
              "content": null
            },
            {
              "number": 4,
              "date": null,
              "status": "PENDING",
              "content": null
            },
            {
              "number": 5,
              "date": null,
              "status": "PENDING",
              "content": null
            },
            {
              "number": 6,
              "date": null,
              "status": "PENDING",
              "content": null
            },
            {
              "number": 7,
              "date": null,
              "status": "PENDING",
              "content": null
            },
            {
              "number": 8,
              "date": null,
              "status": "PENDING",
              "content": null
            }
          ]
        },
        {
          "number": 15,
          "lessons": [
            {
              "number": 1,
              "date": null,
              "status": "PENDING",
              "content": null
            },
            {
              "number": 2,
              "date": null,
              "status": "PENDING",
              "content": null
            },
            {
              "number": 3,
              "date": null,
              "status": "PENDING",
              "content": null
            },
            {
              "number": 4,
              "date": null,
              "status": "PENDING",
              "content": null
            },
            {
              "number": 5,
              "date": null,
              "status": "PENDING",
              "content": null
            },
            {
              "number": 6,
              "date": null,
              "status": "PENDING",
              "content": null
            },
            {
              "number": 7,
              "date": null,
              "status": "PENDING",
              "content": null
            },
            {
              "number": 8,
              "date": null,
              "status": "PENDING",
              "content": null
            }
          ]
        },
        {
          "number": 16,
          "lessons": [
            {
              "number": 1,
              "date": null,
              "status": "PENDING",
              "content": null
            },
            {
              "number": 2,
              "date": null,
              "status": "PENDING",
              "content": null
            },
            {
              "number": 3,
              "date": null,
              "status": "PENDING",
              "content": null
            },
            {
              "number": 4,
              "date": null,
              "status": "PENDING",
              "content": null
            },
            {
              "number": 5,
              "date": null,
              "status": "PENDING",
              "content": null
            },
            {
              "number": 6,
              "date": null,
              "status": "PENDING",
              "content": null
            },
            {
              "number": 7,
              "date": null,
              "status": "PENDING",
              "content": null
            },
            {
              "number": 8,
              "date": null,
              "status": "PENDING",
              "content": null
            }
          ]
        },
        {
          "number": 17,
          "lessons": [
            {
              "number": 1,
              "date": null,
              "status": "PENDING",
              "content": null
            },
            {
              "number": 2,
              "date": null,
              "status": "PENDING",
              "content": null
            },
            {
              "number": 3,
              "date": null,
              "status": "PENDING",
              "content": null
            },
            {
              "number": 4,
              "date": null,
              "status": "PENDING",
              "content": null
            },
            {
              "number": 5,
              "date": null,
              "status": "PENDING",
              "content": null
            },
            {
              "number": 6,
              "date": null,
              "status": "PENDING",
              "content": null
            },
            {
              "number": 7,
              "date": null,
              "status": "PENDING",
              "content": null
            },
            {
              "number": 8,
              "date": null,
              "status": "PENDING",
              "content": null
            }
          ]
        },
        {
          "number": 18,
          "lessons": [
            {
              "number": 1,
              "date": null,
              "status": "PENDING",
              "content": null
            },
            {
              "number": 2,
              "date": null,
              "status": "PENDING",
              "content": null
            },
            {
              "number": 3,
              "date": null,
              "status": "PENDING",
              "content": null
            },
            {
              "number": 4,
              "date": null,
              "status": "PENDING",
              "content": null
            },
            {
              "number": 5,
              "date": null,
              "status": "PENDING",
              "content": null
            },
            {
              "number": 6,
              "date": null,
              "status": "PENDING",
              "content": null
            },
            {
              "number": 7,
              "date": null,
              "status": "PENDING",
              "content": null
            },
            {
              "number": 8,
              "date": null,
              "status": "PENDING",
              "content": null
            }
          ]
        },
        {
          "number": 19,
          "lessons": [
            {
              "number": 1,
              "date": null,
              "status": "PENDING",
              "content": null
            },
            {
              "number": 2,
              "date": null,
              "status": "PENDING",
              "content": null
            },
            {
              "number": 3,
              "date": null,
              "status": "PENDING",
              "content": null
            },
            {
              "number": 4,
              "date": null,
              "status": "PENDING",
              "content": null
            },
            {
              "number": 5,
              "date": null,
              "status": "PENDING",
              "content": null
            },
            {
              "number": 6,
              "date": null,
              "status": "PENDING",
              "content": null
            },
            {
              "number": 7,
              "date": null,
              "status": "PENDING",
              "content": null
            },
            {
              "number": 8,
              "date": null,
              "status": "PENDING",
              "content": null
            }
          ]
        },
        {
          "number": 20,
          "lessons": [
            {
              "number": 1,
              "date": null,
              "status": "PENDING",
              "content": null
            },
            {
              "number": 2,
              "date": null,
              "status": "PENDING",
              "content": null
            },
            {
              "number": 3,
              "date": null,
              "status": "PENDING",
              "content": null
            },
            {
              "number": 4,
              "date": null,
              "status": "PENDING",
              "content": null
            },
            {
              "number": 5,
              "date": null,
              "status": "PENDING",
              "content": null
            },
            {
              "number": 6,
              "date": null,
              "status": "PENDING",
              "content": null
            },
            {
              "number": 7,
              "date": null,
              "status": "PENDING",
              "content": null
            },
            {
              "number": 8,
              "date": null,
              "status": "PENDING",
              "content": null
            }
          ]
        }
      ]
    }
  ]
}